seekret/apitest/__init__.py
seekret/apitest/runprofile.py
seekret/apitest/auth/__init__.py
seekret/apitest/auth/base.py
seekret/apitest/auth/bearer.py
seekret/apitest/auth/factory.py
seekret/apitest/auth/headers.py
seekret/apitest/context/__init__.py
seekret/apitest/context/context.py
seekret/apitest/context/response.py
seekret/apitest/context/session.py
seekret/apitest/fixtures/__init__.py
seekret/apitest/hooks/__init__.py
seekret/apitest/pytest_plugin/__init__.py
seekret/apitest/pytest_plugin/fixtures.py
seekret/apitest/pytest_plugin/newhooks.py
seekret/apitest/pytest_plugin/options.py
seekret.apitest-0.3.1.dist-info/LICENSE
seekret.apitest-0.3.1.dist-info/METADATA
seekret.apitest-0.3.1.dist-info/WHEEL
seekret.apitest-0.3.1.dist-info/entry_points.txt
seekret.apitest-0.3.1.dist-info/top_level.txt
seekret.apitest-0.3.1.dist-info/RECORD
