Metadata-Version: 2.1
Name: seekret.apitest
Version: 0.3.1
Summary: Seekret's library for API testing runtime
Home-page: https://github.com/seek-ret/tests-rtl
Author: Seekret Software Ltd.
Author-email: info@seekret.com
License: UNKNOWN
Project-URL: Bug Tracker, https://github.com/seek-ret/tests-rtl/issues
Platform: UNKNOWN
Classifier: Programming Language :: Python :: 3
Classifier: License :: OSI Approved :: MIT License
Classifier: Operating System :: OS Independent
Requires-Dist: requests (<3,>=2)
Requires-Dist: PyYAML (<6,>=5)
Requires-Dist: jmespath
Requires-Dist: pytest (<7,>=6)
Requires-Dist: pykwalify (~=1.8)
